[
  {
    "rank": "1",
    "entrant": "Mike Duin",
    "entries": "152",
    "titles": "17",
    "topthree": "44",
    "prizes": "$16,779"
  },
  {
    "rank": "2",
    "entrant": "Kyle Davis",
    "entries": "117",
    "titles": "9",
    "topthree": "26.5",
    "prizes": "$14,904"
  },
  {
    "rank": "3",
    "entrant": "Billy Schreyer",
    "entries": "109",
    "titles": "4",
    "topthree": "13",
    "prizes": "$5,217"
  },
  {
    "rank": "4",
    "entrant": "Steve Duin",
    "entries": "103",
    "titles": "2",
    "topthree": "11",
    "prizes": "$1,295"
  },
  {
    "rank": "5",
    "entrant": "Alex Tulipinspring*",
    "entries": "99",
    "titles": "5",
    "topthree": "13",
    "prizes": "$4,945"
  },
  {
    "rank": "6",
    "entrant": "Dan Goldman",
    "entries": "94",
    "titles": "10",
    "topthree": "21",
    "prizes": "$12,864"
  },
  {
    "rank": "7",
    "entrant": "Andrew Gay",
    "entries": "94",
    "titles": "2",
    "topthree": "5",
    "prizes": "$2,176"
  },
  {
    "rank": "8",
    "entrant": "Joe Simich",
    "entries": "93",
    "titles": "4",
    "topthree": "16",
    "prizes": "$6,316"
  },
  {
    "rank": "9",
    "entrant": "Joe Nelson",
    "entries": "68",
    "titles": "3",
    "topthree": "6",
    "prizes": "$3,134"
  },
  {
    "rank": "10",
    "entrant": "Sean Stokke",
    "entries": "65",
    "titles": "2",
    "topthree": "6",
    "prizes": "$1,559"
  }
]
